dxs/__init__.py
dxs/__main__.py
dxs/cli.py
dxs/commands/__init__.py
dxs/commands/api.py
dxs/commands/auth.py
dxs/commands/branch.py
dxs/commands/config.py
dxs/commands/crm.py
dxs/commands/devops.py
dxs/commands/document.py
dxs/commands/env.py
dxs/commands/explore.py
dxs/commands/marketplace.py
dxs/commands/odata.py
dxs/commands/organization.py
dxs/commands/repo.py
dxs/commands/servicepack.py
dxs/commands/source.py
dxs/commands/studio.py
dxs/commands/user.py
dxs/core/__init__.py
dxs/core/cache.py
dxs/core/graph.py
dxs/core/responses.py
dxs/core/api/__init__.py
dxs/core/api/client.py
dxs/core/api/endpoints.py
dxs/core/api/models.py
dxs/core/auth/__init__.py
dxs/core/auth/decorators.py
dxs/core/auth/msal_client.py
dxs/core/auth/token_cache.py
dxs/core/devops/__init__.py
dxs/core/devops/client.py
dxs/core/devops/models.py
dxs/core/dynamics/__init__.py
dxs/core/dynamics/client.py
dxs/core/footprint/__init__.py
dxs/core/footprint/client.py
dxs/core/footprint/edmx_parser.py
dxs/core/footprint/metadata.py
dxs/core/output/__init__.py
dxs/core/output/csv_fmt.py
dxs/core/output/formatter.py
dxs/core/output/json_fmt.py
dxs/core/output/yaml_fmt.py
dxs/models/__init__.py
dxs/utils/__init__.py
dxs/utils/click_options.py
dxs/utils/config.py
dxs/utils/errors.py
dxs/utils/filtering.py
dxs/utils/paths.py
dxs/utils/resolvers.py
dxs/utils/responses.py
dxs/utils/restricted.py
dxs/utils/sorting.py
dxs/web/__init__.py
dxs/web/app.py
datex_studio_cli-0.1.14.dist-info/METADATA
datex_studio_cli-0.1.14.dist-info/WHEEL
datex_studio_cli-0.1.14.dist-info/entry_points.txt
datex_studio_cli-0.1.14.dist-info/RECORD
