Metadata-Version: 2.4
Name: datex-studio-cli
Version: 0.1.14
Summary: CLI for Datex Studio low-code platform, designed for LLM-based AI agents
Project-URL: Homepage, https://github.com/datex/datex-studio-cli
Project-URL: Documentation, https://github.com/datex/datex-studio-cli
Project-URL: Repository, https://github.com/datex/datex-studio-cli
Author: Datex
License-Expression: MIT
Keywords: ai,cli,datex,llm,low-code
Classifier: Development Status :: 3 - Alpha
Classifier: Environment :: Console
Classifier: Intended Audience :: Developers
Classifier: License :: OSI Approved :: MIT License
Classifier: Operating System :: OS Independent
Classifier: Programming Language :: Python :: 3
Classifier: Programming Language :: Python :: 3.10
Classifier: Programming Language :: Python :: 3.11
Classifier: Programming Language :: Python :: 3.12
Classifier: Topic :: Software Development :: Libraries :: Application Frameworks
Requires-Python: >=3.10
Requires-Dist: click>=8.1.0
Requires-Dist: httpx>=0.27.0
Requires-Dist: markdownify>=0.13.0
Requires-Dist: msal>=1.28.0
Requires-Dist: pydantic-settings>=2.0.0
Requires-Dist: pydantic>=2.5.0
Requires-Dist: pyyaml>=6.0
Provides-Extra: dev
Requires-Dist: mypy>=1.8.0; extra == 'dev'
Requires-Dist: pytest-cov>=4.0.0; extra == 'dev'
Requires-Dist: pytest-httpx>=0.30.0; extra == 'dev'
Requires-Dist: pytest>=8.0.0; extra == 'dev'
Requires-Dist: ruff>=0.4.0; extra == 'dev'
Requires-Dist: types-pyyaml>=6.0.0; extra == 'dev'
Provides-Extra: studio
Requires-Dist: fastapi>=0.115.0; extra == 'studio'
Requires-Dist: uvicorn[standard]>=0.32.0; extra == 'studio'
